flashcardscode/__init__.py
flashcardscode/accountlogin.py
flashcardscode/config.py
flashcardscode/deletion.py
flashcardscode/main.py
flashcardscode/setcreation.py
flashcardscode/studyoptions.py
Flashcards_Terminal_App-0.0.1.dist-info/METADATA
Flashcards_Terminal_App-0.0.1.dist-info/WHEEL
Flashcards_Terminal_App-0.0.1.dist-info/top_level.txt
Flashcards_Terminal_App-0.0.1.dist-info/RECORD
